device_utils.py
download_utils.py
ffmpeg_utils.py
file_utils.py
gemini_utils.py
legen.py
legen_cli.py
subtitle_utils.py
translate_utils.py
utils.py
whisper_utils.py
whisperx_utils.py
legen-0.20.0.dist-info/licenses/LICENSE
legen-0.20.0.dist-info/METADATA
legen-0.20.0.dist-info/WHEEL
legen-0.20.0.dist-info/entry_points.txt
legen-0.20.0.dist-info/top_level.txt
legen-0.20.0.dist-info/RECORD
