Metadata-Version: 2.4
Name: legen
Version: 0.20.0
Summary: Powerfull toolkit that locally transcribes, translates, and masters subtitles for your media
Author: Matheus Bach
License-Expression: GPL-3.0-only
Project-URL: Homepage, https://github.com/matheusbach/legen
Project-URL: Issue Tracker, https://github.com/matheusbach/legen/issues
Keywords: subtitles,whisper,translation,ffmpeg,yt-dlp
Classifier: Development Status :: 4 - Beta
Classifier: Environment :: Console
Classifier: Intended Audience :: End Users/Desktop
Classifier: Intended Audience :: Developers
Classifier: Programming Language :: Python :: 3
Classifier: Programming Language :: Python :: 3.9
Classifier: Programming Language :: Python :: 3.10
Classifier: Programming Language :: Python :: 3.11
Classifier: Programming Language :: Python :: 3.12
Classifier: Topic :: Multimedia :: Video
Requires-Python: <3.13,>=3.9
License-File: LICENSE
Requires-Dist: deep-translator
Requires-Dist: ffmpeg-progress-yield
Requires-Dist: openai-whisper
Requires-Dist: pysrt
Requires-Dist: torch
Requires-Dist: torchaudio<2.9
Requires-Dist: tqdm
Requires-Dist: whisper
Requires-Dist: vidqa
Requires-Dist: gemini-srt-translator
Requires-Dist: google-generativeai
Requires-Dist: yt-dlp
Requires-Dist: whisperx-legen-fork
Provides-Extra: dev
Requires-Dist: pytest>=8; extra == "dev"
Dynamic: license-file
